[
  {
    "name": "Aarav Sharma",
    "age": 28,
    "blood_group": "O+",
    "phone": "9876543210",
    "city": "Delhi",
    "distance": "2.3 km",
    "availability": true
  },
  {
    "name": "Priya Patel",
    "age": 34,
    "blood_group": "A+",
    "phone": "8765432109",
    "city": "Mumbai",
    "distance": "1.5 km",
    "availability": true
  },
  {
    "name": "Rohan Gupta",
    "age": 22,
    "blood_group": "B+",
    "phone": "7654321098",
    "city": "Bengaluru",
    "distance": "4.1 km",
    "availability": true
  },
  {
    "name": "Sneha Iyer",
    "age": 30,
    "blood_group": "AB+",
    "phone": "9988776655",
    "city": "Chennai",
    "distance": "3.7 km",
    "availability": true
  },
  {
    "name": "Vikram Singh",
    "age": 45,
    "blood_group": "O-",
    "phone": "8877665544",
    "city": "Delhi",
    "distance": "5.2 km",
    "availability": true
  },
  {
    "name": "Ananya Reddy",
    "age": 26,
    "blood_group": "A-",
    "phone": "7766554433",
    "city": "Hyderabad",
    "distance": "2.8 km",
    "availability": true
  },
  {
    "name": "Karthik Nair",
    "age": 38,
    "blood_group": "B-",
    "phone": "6655443322",
    "city": "Kochi",
    "distance": "1.9 km",
    "availability": true
  },
  {
    "name": "Meera Joshi",
    "age": 29,
    "blood_group": "AB-",
    "phone": "9123456789",
    "city": "Pune",
    "distance": "3.4 km",
    "availability": true
  },
  {
    "name": "Arjun Kapoor",
    "age": 31,
    "blood_group": "O+",
    "phone": "8234567890",
    "city": "Mumbai",
    "distance": "6.1 km",
    "availability": true
  },
  {
    "name": "Divya Menon",
    "age": 24,
    "blood_group": "A+",
    "phone": "7345678901",
    "city": "Bengaluru",
    "distance": "0.8 km",
    "availability": true
  },
  {
    "name": "Rajesh Kumar",
    "age": 50,
    "blood_group": "B+",
    "phone": "9456789012",
    "city": "Kolkata",
    "distance": "4.6 km",
    "availability": false
  },
  {
    "name": "Lakshmi Sundaram",
    "age": 33,
    "blood_group": "AB+",
    "phone": "8567890123",
    "city": "Chennai",
    "distance": "2.0 km",
    "availability": true
  },
  {
    "name": "Aditya Verma",
    "age": 27,
    "blood_group": "O-",
    "phone": "7678901234",
    "city": "Jaipur",
    "distance": "7.3 km",
    "availability": true
  },
  {
    "name": "Pooja Deshmukh",
    "age": 36,
    "blood_group": "A-",
    "phone": "6789012345",
    "city": "Pune",
    "distance": "1.2 km",
    "availability": true
  },
  {
    "name": "Suresh Pillai",
    "age": 42,
    "blood_group": "B-",
    "phone": "9890123456",
    "city": "Thiruvananthapuram",
    "distance": "5.5 km",
    "availability": false
  },
  {
    "name": "Nandini Rao",
    "age": 19,
    "blood_group": "AB-",
    "phone": "8901234567",
    "city": "Hyderabad",
    "distance": "3.1 km",
    "availability": true
  },
  {
    "name": "Harsh Agarwal",
    "age": 25,
    "blood_group": "O+",
    "phone": "7012345678",
    "city": "Lucknow",
    "distance": "2.9 km",
    "availability": true
  },
  {
    "name": "Sanya Malhotra",
    "age": 32,
    "blood_group": "A+",
    "phone": "9234567801",
    "city": "Delhi",
    "distance": "1.1 km",
    "availability": true
  },
  {
    "name": "Deepak Choudhary",
    "age": 48,
    "blood_group": "B+",
    "phone": "8345678902",
    "city": "Ahmedabad",
    "distance": "4.8 km",
    "availability": true
  },
  {
    "name": "Ritu Saxena",
    "age": 23,
    "blood_group": "AB+",
    "phone": "7456789013",
    "city": "Bhopal",
    "distance": "6.7 km",
    "availability": true
  },
  {
    "name": "Manish Tiwari",
    "age": 40,
    "blood_group": "O-",
    "phone": "6567890124",
    "city": "Chandigarh",
    "distance": "3.5 km",
    "availability": true
  },
  {
    "name": "Kavita Bhatt",
    "age": 35,
    "blood_group": "A-",
    "phone": "9678901235",
    "city": "Dehradun",
    "distance": "8.0 km",
    "availability": false
  },
  {
    "name": "Siddharth Mukherjee",
    "age": 29,
    "blood_group": "B-",
    "phone": "8789012346",
    "city": "Kolkata",
    "distance": "2.4 km",
    "availability": true
  },
  {
    "name": "Tanvi Kulkarni",
    "age": 21,
    "blood_group": "AB-",
    "phone": "7890123457",
    "city": "Nagpur",
    "distance": "1.7 km",
    "availability": true
  },
  {
    "name": "Amit Pandey",
    "age": 55,
    "blood_group": "O+",
    "phone": "9901234568",
    "city": "Varanasi",
    "distance": "5.0 km",
    "availability": true
  },
  {
    "name": "Ishita Banerjee",
    "age": 27,
    "blood_group": "A+",
    "phone": "8012345679",
    "city": "Kolkata",
    "distance": "3.3 km",
    "availability": true
  },
  {
    "name": "Gaurav Mishra",
    "age": 37,
    "blood_group": "B+",
    "phone": "7123456780",
    "city": "Patna",
    "distance": "4.2 km",
    "availability": true
  },
  {
    "name": "Swati Deshpande",
    "age": 30,
    "blood_group": "AB+",
    "phone": "6234567891",
    "city": "Mumbai",
    "distance": "0.5 km",
    "availability": true
  },
  {
    "name": "Nikhil Hegde",
    "age": 44,
    "blood_group": "O-",
    "phone": "9345678902",
    "city": "Bengaluru",
    "distance": "6.9 km",
    "availability": false
  },
  {
    "name": "Anjali Chauhan",
    "age": 18,
    "blood_group": "A-",
    "phone": "8456789013",
    "city": "Indore",
    "distance": "2.6 km",
    "availability": true
  },
  {
    "name": "Pranav Shetty",
    "age": 33,
    "blood_group": "B-",
    "phone": "7567890124",
    "city": "Mangalore",
    "distance": "1.4 km",
    "availability": true
  },
  {
    "name": "Neha Chatterjee",
    "age": 26,
    "blood_group": "AB-",
    "phone": "6678901235",
    "city": "Guwahati",
    "distance": "9.1 km",
    "availability": true
  },
  {
    "name": "Test Donor Playwright",
    "age": 30,
    "blood_group": "O-",
    "phone": "9998887770",
    "city": "Bengaluru",
    "area": "Indiranagar",
    "availability": true,
    "last_donation_date": ""
  },
  {
    "name": "Sneha",
    "age": 30,
    "blood_group": "O+",
    "phone": "9964767664",
    "city": "Bengaluru",
    "area": "Konanakunte",
    "availability": true,
    "last_donation_date": ""
  },
  {
    "name": "Suhas",
    "age": 23,
    "blood_group": "B+",
    "phone": "1234567896",
    "city": "Bengaluru",
    "area": "Doddaballapur",
    "availability": true,
    "last_donation_date": ""
  },
  {
    "name": "Jane",
    "age": 23,
    "blood_group": "O+",
    "phone": "234563433",
    "city": "Bengaluru",
    "area": "Konanakunte",
    "availability": true,
    "last_donation_date": ""
  },
  {
    "name": "Dough",
    "age": 23,
    "blood_group": "O+",
    "phone": "1234",
    "city": "Bengaluru",
    "area": "Konanakunte",
    "availability": true,
    "last_donation_date": ""
  },
  {
    "name": "doe",
    "age": 21,
    "blood_group": "O+",
    "phone": "9036767664",
    "city": "Bengaluru",
    "area": "Konanakunte",
    "availability": true,
    "last_donation_date": ""
  }
]